sanwei/__about__.py
sanwei/__init__.py
sanwei/__main__.py
sanwei/cli.py
sanwei-0.0.1.dist-info/METADATA
sanwei-0.0.1.dist-info/WHEEL
sanwei-0.0.1.dist-info/entry_points.txt
sanwei-0.0.1.dist-info/licenses/LICENSE.txt
sanwei-0.0.1.dist-info/RECORD
