Metadata-Version: 2.1
Name: sanwei
Version: 0.0.1
Summary: Render random chinese text in 3D
Project-URL: Documentation, https://github.com/fetsorn/sanwei#readme
Project-URL: Issues, https://github.com/fetsorn/sanwei/issues
Project-URL: Source, https://github.com/fetsorn/sanwei
Author-email: Anton Davydov <fetsorn@gmail.com>
License-Expression: MIT
License-File: LICENSE.txt
Classifier: Development Status :: 4 - Beta
Classifier: Programming Language :: Python
Classifier: Programming Language :: Python :: 3.10
Classifier: Programming Language :: Python :: 3.11
Classifier: Programming Language :: Python :: Implementation :: CPython
Classifier: Programming Language :: Python :: Implementation :: PyPy
Requires-Python: >=3.10
Requires-Dist: bpy>=3.5
